tarea4/rtl/spi2parallel.v
// https://www.fpga4fun.com/SPI2.html
// N bits SPI receiver, Mode 0.
//
// ss = 1;
// #10
// Reception doesn't end until N bits are received. This enables receiving
// separate bytes.
// Once reception ended, rxend will set for one clock cycle.
module spi(clk, mosi, sck, ss, rst, dout, rxend);
  parameter N = 16;
  input clk;
  input mosi;
  input sck;
  input ss;
  input rst;
  output [N-1:0] dout;
  output reg rxend;

  reg [N-1:0] shiftreg;
  reg [N-1:0] counter;
  reg [2:0] sckreg;
  reg [2:0] ssreg;
  reg halt;
  wire sck_rising;
  wire ss_rising;
  wire ss_falling;

  // Sync with clk
  always @(posedge clk) begin
    sckreg <= {sckreg[1:0], sck};
    ssreg  <= {ssreg[1:0], ss};
  end

  assign sck_rising  = (sckreg[2:1] == 2'b01);
  assign sck_falling = (sckreg[2:1] == 2'b10);
  assign ss_rising   = (ssreg[2:1] == 2'b01);
  assign ss_falling  = (ssreg[2:1] == 2'b10);

  // Main
  always @(posedge clk or rst) begin
    if (~rst) begin
      shiftreg <= 0;
      counter <= 0;
      rxend <= 0;
    end
    // Receiving mode
    else if (!ss) begin
      // RX starting
      if (ss_falling & rxend) begin
        shiftreg <= 0;
        counter <= 0;
        rxend <= 0;
      end
      // RX ended
      else if (halt) begin
        rxend <= 0; // Reset rxend
      end
      // Sample bit
      else if (sck_rising) begin
        shiftreg[0] <= mosi;
        counter = counter + 1;
      end
      // Shift
      else if (sck_falling) begin
        shiftreg = shiftreg << 1;
        if (counter == N) begin
          halt <= 1;
          rxend <= 1;
        end
      end
    end

    // IDLE mode
    else if (ss) begin
      // RX ended
      if (halt) begin
        rxend <= 0; // Reset rxend
      end
      if (ss_rising) begin
      end
    end
  end

assign dout = shiftreg;


endmodule

tarea4/testbench/spi/spi_tb.v
`timescale 1ns/1ns
module spi_tb();

parameter N = 16;

initial begin
  $dumpfile("spi_tb.vcd");
  $dumpvars(0, spi_tb);
end

reg clk;
reg mosi;
reg sck;
reg ss;
reg rst;
wire [N-1:0] dout;
wire rxend;

integer i;
reg [8:0] digit1;
reg [8:0] digit2;

spi #(.N(N))

  uut(.clk(clk),
      .mosi(mosi),
      .sck(sck),
      .ss(ss),
      .rst(rst),
      .dout(dout),
      .rxend(rxend)
  );

initial begin
  clk = 0;
end

always #1 clk = ~clk;

initial begin

  rst = 1;
  mosi = 0;
  sck = 0;
  ss = 1;
  #2;

  rst = 0;
  #2;

  ss = 0;
  digit1 = 8'd24;
  for (i = 0; i < 8; i = i + 1) begin
    mosi = digit1[i];
    #10;
    sck = 1;
    #10;
    sck = 0;
    #10;
  end

  digit2 = 8'd8;
  for (i = 0; i < 8; i = i + 1) begin
    mosi = digit1[i];
    #10;
    sck = 1;
    #10;
    sck = 0;
    #10;
  end

  ss = 1;
  #10;

  ss = 0;
  #10;

  $finish;
end

endmodule

tarea4/testbench/spi/spi_tb.vcd
$date
	Mon May 11 17:40:13 2020
$end
$version
	Icarus Verilog
$end
$timescale
	1ns
$end
$scope module spi_tb $end
$var wire 1 ! rxend $end
$var wire 16 " dout [15:0] $end
$var reg 1 # clk $end
$var reg 9 $ digit1 [8:0] $end
$var reg 9 % digit2 [8:0] $end
$var reg 1 & mosi $end
$var reg 1 ' rst $end
$var reg 1 ( sck $end
$var reg 1 ) ss $end
$var integer 32 * i [31:0] $end
$scope module uut $end
$var wire 1 # clk $end
$var wire 16 + dout [15:0] $end
$var wire 1 & mosi $end
$var wire 1 ' rst $end
$var wire 1 ( sck $end
$var wire 1 ) ss $end
$var wire 1 , ss_rising $end
$var wire 1 - ss_falling $end
$var wire 1 . sck_rising $end
$var wire 1 / sck_falling $end
$var reg 16 0 counter [15:0] $end
$var reg 1 1 halt $end
$var reg 1 ! rxend $end
$var reg 3 2 sckreg [2:0] $end
$var reg 16 3 shiftreg [15:0] $end
$var reg 3 4 ssreg [2:0] $end
$upscope $end
$upscope $end
$enddefinitions $end
#0
$dumpvars
bx 4
b0 3
bx 2
x1
b0 0
x/
x.
x-
x,
b0 +
bx *
1)
0(
1'
0&
bx %
bx $
0#
b0 "
0!
$end
#1
bx1 4
bx0 2
1#
#2
0#
0'
#3
0-
0.
bx11 4
bx00 2
1#
#4
0#
b0 *
b11000 $
0)
#5
0,
0/
b110 4
b0 2
1#
#6
0#
#7
1-
b100 4
1#
#8
0#
#9
0-
b0 4
1#
#10
0#
#11
1#
#12
0#
#13
1#
#14
0#
1(
#15
b1 2
1#
#16
0#
#17
1.
b11 2
1#
#18
0#
#19
0.
b111 2
b1 0
1#
#20
0#
#21
1#
#22
0#
#23
1#
#24
0#
0(
#25
b110 2
1#
#26
0#
#27
1/
b100 2
1#
#28
0#
#29
0/
b0 2
1#
#30
0#
#31
1#
#32
0#
#33
1#
#34
0#
b1 *
#35
1#
#36
0#
#37
1#
#38
0#
#39
1#
#40
0#
#41
1#
#42
0#
#43
1#
#44
0#
1(
#45
b1 2
1#
#46
0#
#47
1.
b11 2
1#
#48
0#
#49
0.
b111 2
b10 0
1#
#50
0#
#51
1#
#52
0#
#53
1#
#54
0#
0(
#55
b110 2
1#
#56
0#
#57
1/
b100 2
1#
#58
0#
#59
0/
b0 2
1#
#60
0#
#61
1#
#62
0#
#63
1#
#64
0#
b10 *
#65
1#
#66
0#
#67
1#
#68
0#
#69
1#
#70
0#
#71
1#
#72
0#
#73
1#
#74
0#
1(
#75
b1 2
1#
#76
0#
#77
1.
b11 2
1#
#78
0#
#79
0.
b111 2
b11 0
1#
#80
0#
#81
1#
#82
0#
#83
1#
#84
0#
0(
#85
b110 2
1#
#86
0#
#87
1/
b100 2
1#
#88
0#
#89
0/
b0 2
1#
#90
0#
#91
1#
#92
0#
#93
1#
#94
0#
1&
b11 *
#95
1#
#96
0#
#97
1#
#98
0#
#99
1#
#100
0#
#101
1#
#102
0#
#103
1#
#104
0#
1(
#105
b1 2
1#
#106
0#
#107
1.
b11 2
1#
#108
0#
#109
0.
b1 "
b1 +
b1 3
b111 2
b100 0
1#
#110
0#
#111
1#
#112
0#
#113
1#
#114
0#
0(
#115
b110 2
1#
#116
0#
#117
1/
b100 2
1#
#118
0#
#119
0/
b0 2
b10 "
b10 +
b10 3
1#
#120
0#
#121
1#
#122
0#
#123
1#
#124
0#
b100 *
#125
1#
#126
0#
#127
1#
#128
0#
#129
1#
#130
0#
#131
1#
#132
0#
#133
1#
#134
0#
1(
#135
b1 2
1#
#136
0#
#137
1.
b11 2
1#
#138
0#
#139
0.
b11 "
b11 +
b11 3
b111 2
b101 0
1#
#140
0#
#141
1#
#142
0#
#143
1#
#144
0#
0(
#145
b110 2
1#
#146
0#
#147
1/
b100 2
1#
#148
0#
#149
0/
b0 2
b110 "
b110 +
b110 3
1#
#150
0#
#151
1#
#152
0#
#153
1#
#154
0#
0&
b101 *
#155
1#
#156
0#
#157
1#
#158
0#
#159
1#
#160
0#
#161
1#
#162
0#
#163
1#
#164
0#
1(
#165
b1 2
1#
#166
0#
#167
1.
b11 2
1#
#168
0#
#169
0.
b111 2
b110 0
1#
#170
0#
#171
1#
#172
0#
#173
1#
#174
0#
0(
#175
b110 2
1#
#176
0#
#177
1/
b100 2
1#
#178
0#
#179
0/
b0 2
b1100 "
b1100 +
b1100 3
1#
#180
0#
#181
1#
#182
0#
#183
1#
#184
0#
b110 *
#185
1#
#186
0#
#187
1#
#188
0#
#189
1#
#190
0#
#191
1#
#192
0#
#193
1#
#194
0#
1(
#195
b1 2
1#
#196
0#
#197
1.
b11 2
1#
#198
0#
#199
0.
b111 2
b111 0
1#
#200
0#
#201
1#
#202
0#
#203
1#
#204
0#
0(
#205
b110 2
1#
#206
0#
#207
1/
b100 2
1#
#208
0#
#209
0/
b0 2
b11000 "
b11000 +
b11000 3
1#
#210
0#
#211
1#
#212
0#
#213
1#
#214
0#
b111 *
#215
1#
#216
0#
#217
1#
#218
0#
#219
1#
#220
0#
#221
1#
#222
0#
#223
1#
#224
0#
1(
#225
b1 2
1#
#226
0#
#227
1.
b11 2
1#
#228
0#
#229
0.
b111 2
b1000 0
1#
#230
0#
#231
1#
#232
0#
#233
1#
#234
0#
0(
#235
b110 2
1#
#236
0#
#237
1/
b100 2
1#
#238
0#
#239
0/
b0 2
b110000 "
b110000 +
b110000 3
1#
#240
0#
#241
1#
#242
0#
#243
1#
#244
0#
b1000 %
b0 *
#245
1#
#246
0#
#247
1#
#248
0#
#249
1#
#250
0#
#251
1#
#252
0#
#253
1#
#254
0#
1(
#255
b1 2
1#
#256
0#
#257
1.
b11 2
1#
#258
0#
#259
0.
b111 2
b1001 0
1#
#260
0#
#261
1#
#262
0#
#263
1#
#264
0#
0(
#265
b110 2
1#
#266
0#
#267
1/
b100 2
1#
#268
0#
#269
0/
b0 2
b1100000 "
b1100000 +
b1100000 3
1#
#270
0#
#271
1#
#272
0#
#273
1#
#274
0#
b1 *
#275
1#
#276
0#
#277
1#
#278
0#
#279
1#
#280
0#
#281
1#
#282
0#
#283
1#
#284
0#
1(
#285
b1 2
1#
#286
0#
#287
1.
b11 2
1#
#288
0#
#289
0.
b111 2
b1010 0
1#
#290
0#
#291
1#
#292
0#
#293
1#
#294
0#
0(
#295
b110 2
1#
#296
0#
#297
1/
b100 2
1#
#298
0#
#299
0/
b0 2
b11000000 "
b11000000 +
b11000000 3
1#
#300
0#
#301
1#
#302
0#
#303
1#
#304
0#
b10 *
#305
1#
#306
0#
#307
1#
#308
0#
#309
1#
#310
0#
#311
1#
#312
0#
#313
1#
#314
0#
1(
#315
b1 2
1#
#316
0#
#317
1.
b11 2
1#
#318
0#
#319
0.
b111 2
b1011 0
1#
#320
0#
#321
1#
#322
0#
#323
1#
#324
0#
0(
#325
b110 2
1#
#326
0#
#327
1/
b100 2
1#
#328
0#
#329
0/
b0 2
b110000000 "
b110000000 +
b110000000 3
1#
#330
0#
#331
1#
#332
0#
#333
1#
#334
0#
1&
b11 *
#335
1#
#336
0#
#337
1#
#338
0#
#339
1#
#340
0#
#341
1#
#342
0#
#343
1#
#344
0#
1(
#345
b1 2
1#
#346
0#
#347
1.
b11 2
1#
#348
0#
#349
0.
b110000001 "
b110000001 +
b110000001 3
b111 2
b1100 0
1#
#350
0#
#351
1#
#352
0#
#353
1#
#354
0#
0(
#355
b110 2
1#
#356
0#
#357
1/
b100 2
1#
#358
0#
#359
0/
b0 2
b1100000010 "
b1100000010 +
b1100000010 3
1#
#360
0#
#361
1#
#362
0#
#363
1#
#364
0#
b100 *
#365
1#
#366
0#
#367
1#
#368
0#
#369
1#
#370
0#
#371
1#
#372
0#
#373
1#
#374
0#
1(
#375
b1 2
1#
#376
0#
#377
1.
b11 2
1#
#378
0#
#379
0.
b1100000011 "
b1100000011 +
b1100000011 3
b111 2
b1101 0
1#
#380
0#
#381
1#
#382
0#
#383
1#
#384
0#
0(
#385
b110 2
1#
#386
0#
#387
1/
b100 2
1#
#388
0#
#389
0/
b0 2
b11000000110 "
b11000000110 +
b11000000110 3
1#
#390
0#
#391
1#
#392
0#
#393
1#
#394
0#
0&
b101 *
#395
1#
#396
0#
#397
1#
#398
0#
#399
1#
#400
0#
#401
1#
#402
0#
#403
1#
#404
0#
1(
#405
b1 2
1#
#406
0#
#407
1.
b11 2
1#
#408
0#
#409
0.
b111 2
b1110 0
1#
#410
0#
#411
1#
#412
0#
#413
1#
#414
0#
0(
#415
b110 2
1#
#416
0#
#417
1/
b100 2
1#
#418
0#
#419
0/
b0 2
b110000001100 "
b110000001100 +
b110000001100 3
1#
#420
0#
#421
1#
#422
0#
#423
1#
#424
0#
b110 *
#425
1#
#426
0#
#427
1#
#428
0#
#429
1#
#430
0#
#431
1#
#432
0#
#433
1#
#434
0#
1(
#435
b1 2
1#
#436
0#
#437
1.
b11 2
1#
#438
0#
#439
0.
b111 2
b1111 0
1#
#440
0#
#441
1#
#442
0#
#443
1#
#444
0#
0(
#445
b110 2
1#
#446
0#
#447
1/
b100 2
1#
#448
0#
#449
0/
b0 2
b1100000011000 "
b1100000011000 +
b1100000011000 3
1#
#450
0#
#451
1#
#452
0#
#453
1#
#454
0#
b111 *
#455
1#
#456
0#
#457
1#
#458
0#
#459
1#
#460
0#
#461
1#
#462
0#
#463
1#
#464
0#
1(
#465
b1 2
1#
#466
0#
#467
1.
b11 2
1#
#468
0#
#469
0.
b111 2
b10000 0
1#
#470
0#
#471
1#
#472
0#
#473
1#
#474
0#
0(
#475
b110 2
1#
#476
0#
#477
1/
b100 2
1#
#478
0#
#479
0/
1!
11
b0 2
b11000000110000 "
b11000000110000 +
b11000000110000 3
1#
#480
0#
#481
0!
1#
#482
0#
#483
1#
#484
0#
1)
b1000 *
#485
b1 4
1#
#486
0#
#487
1,
b11 4
1#
#488
0#
#489
0,
b111 4
1#
#490
0#
#491
1#
#492
0#
#493
1#
#494
0#
0)
#495
b110 4
1#
#496
0#
#497
1-
b100 4
1#
#498
0#
#499
0-
b0 4
1#
