tarea2/rtl/asr8/asr8.v
// https://www.manualslib.com/manual/195956/Xilinx-System-Generator-V2-1.html?page=26#manual
module asr8(clk, rst, din, dout, addr);
  parameter N = 8;
  input clk;
  input rst;
  input  [N-1:0] din;
  output [N-1:0] dout;
  input  [2:0]   addr;

  // https://www.verilogpro.com/verilog-arrays-plain-simple/
  reg [N:0] regarray [7:0]; // Register array
  integer i;

  always @(posedge clk or negedge rst) begin
    //Shift routine
    if (~rst) begin
      for (i = 0; i < 8; i = i + 1) begin
        regarray[i] <= 0;
      end
    end
    // Array shift
    // https://stackoverflow.com/questions/15579020/shifting-2d-array-verilog
    else begin
      for (i = 7; i > 0; i = i - 1) begin
        regarray[i] <= regarray[i-1];
      end
      regarray[0] <= din;
    end
  end

  // Output
  assign dout = regarray[addr];

endmodule

tarea1/testbench/asr8/asr8_tb.v
`timescale 1ns/1ns
module asr8_tb();

parameter N = 8;

initial begin
  $dumpfile("asr8_tb.vcd");
  $dumpvars(0, asr8_tb);
end

reg clk;
reg rst;
reg [N-1:0] din;
reg [2:0] addr;
wire [N-1:0] dout;

asr8 #(.N(N))

            uut(.clk(clk),
                .rst(rst),
                .din(din),
                .dout(dout),
                .addr(addr)
            );

initial begin
    clk = 0;
end

always #5 clk = ~clk;

initial begin
  addr = 0;
  rst = 0;
  #10

  rst = 1;
  #10

  din = 1;
  #10

  din = 2;
  #10

  din = 4;
  #10

  din = 8;
  #10

  din = 8'd16;
  #10

  din = 8'd32;
  #10

  din = 8'd64;
  #10
  addr = 6;

  #50

  $finish;
end

initial begin
  $monitor("t=%t ns,%d%d%d%d%d", $time, clk, rst, din, addr, dout);
end

endmodule

tarea1/testbench/asr8/asr8_tb.vcd
$date
	Sat Mar 21 19:51:37 2020
$end
$version
	Icarus Verilog
$end
$timescale
	1ns
$end
$scope module asr8_tb $end
$var wire 8 ! dout [7:0] $end
$var reg 3 " addr [2:0] $end
$var reg 1 # clk $end
$var reg 8 $ din [7:0] $end
$var reg 1 % rst $end
$scope module uut $end
$var wire 3 & addr [2:0] $end
$var wire 1 # clk $end
$var wire 8 ' din [7:0] $end
$var wire 1 % rst $end
$var wire 8 ( dout [7:0] $end
$var integer 32 ) i [31:0] $end
$upscope $end
$upscope $end
$enddefinitions $end
#0
$dumpvars
b1000 )
b0 (
bx '
b0 &
0%
bx $
0#
b0 "
b0 !
$end
#5
b1000 )
1#
#10
0#
1%
#15
bx !
bx (
b0 )
1#
#20
0#
b1 $
b1 '
#25
b1 !
b1 (
b0 )
1#
#30
0#
b10 $
b10 '
#35
b10 !
b10 (
b0 )
1#
#40
0#
b100 $
b100 '
#45
b100 !
b100 (
b0 )
1#
#50
0#
b1000 $
b1000 '
#55
b1000 !
b1000 (
b0 )
1#
#60
0#
b10000 $
b10000 '
#65
b10000 !
b10000 (
b0 )
1#
#70
0#
b100000 $
b100000 '
#75
b100000 !
b100000 (
b0 )
1#
#80
0#
b1000000 $
b1000000 '
#85
b1000000 !
b1000000 (
b0 )
1#
#90
b1 !
b1 (
0#
b110 "
b110 &
#95
b10 !
b10 (
b0 )
1#
#100
0#
#105
b100 !
b100 (
b0 )
1#
#110
0#
#115
b1000 !
b1000 (
b0 )
1#
#120
0#
#125
b10000 !
b10000 (
b0 )
1#
#130
0#
#135
b100000 !
b100000 (
b0 )
1#
