tarea4/rtl/mult.v
module mult(clk, din1, din2, start, rst, dout, ovf, ready);
  parameter N = 8;
  input clk;
  input [N-1:0] din1;
  input [N-1:0] din2;
  input start;
  input rst;
  output [N-1:0] dout;
  output ovf;
  output reg ready;

  reg [2*N-1:0] result;

  always @(posedge clk) begin
    if (~rst) begin
      result <= 0;
    end
    else if (ready) begin
      ready <= 0;
    end
    else if (start) begin
      result <= din1 * din2;
      ready <= 1;
    end
  end

  // Outputs
  assign ovf = result[2*N-1:N] > 0;
  assign dout = ovf ? {N{1'b1}} : result[N-1:0];

  endmodule

tarea4/rtl/spi2parallel.v
// https://www.fpga4fun.com/SPI2.html
// N bits SPI receiver, Mode 0.
//
// ss = 1;
// #10
// Reception doesn't end until N bits are received. This enables receiving
// separate bytes.
// Once reception ended, rxend will set for one clock cycle.
module spi(clk, mosi, sck, ss, rst, dout, rxend);
  parameter N = 16;
  input clk;
  input mosi;
  input sck;
  input ss;
  input rst;
  output [N-1:0] dout;
  output reg rxend;

  reg [N-1:0] shiftreg;
  reg [N-1:0] counter;
  reg [2:0] sckreg;
  reg [2:0] ssreg;
  reg halt;
  wire sck_rising;
  wire ss_rising;
  wire ss_falling;

  // Sync with clk
  always @(posedge clk) begin
    sckreg <= {sckreg[1:0], sck};
    ssreg  <= {ssreg[1:0], ss};
  end

  assign sck_rising  = (sckreg[2:1] == 2'b01);
  assign sck_falling = (sckreg[2:1] == 2'b10);
  assign ss_rising   = (ssreg[2:1] == 2'b01);
  assign ss_falling  = (ssreg[2:1] == 2'b10);

  // Main
  always @(posedge clk or rst) begin
    if (~rst) begin
      shiftreg <= 0;
      counter <= 0;
      rxend <= 0;
    end
    // Receiving mode
    else if (!ss) begin
      // RX starting
      if (ss_falling & rxend) begin
        shiftreg <= 0;
        counter <= 0;
        rxend <= 0;
      end
      // RX ended
      else if (halt) begin
        rxend <= 0; // Reset rxend
      end
      // Sample bit
      else if (sck_rising) begin
        shiftreg[0] <= mosi;
        counter = counter + 1;
      end
      // Shift
      else if (sck_falling) begin
        shiftreg = shiftreg << 1;
        if (counter == N) begin
          halt <= 1;
          rxend <= 1;
        end
      end
    end

    // IDLE mode
    else if (ss) begin
      // RX ended
      if (halt) begin
        rxend <= 0; // Reset rxend
      end
      if (ss_rising) begin
      end
    end
  end

assign dout = shiftreg;


endmodule

tarea4/rtl/top.v
module top(clk, rst, mosi, ss, sck, dout, ready, ovf);
  parameter N = 8;
  input clk;
  input rst;
  input mosi;
  input ss;
  input sck;
  output [N-1:0] dout;
  output ready;
  output ovf;

  wire [2*N-1:0] spi_out;
  wire rxend;
  reg [N-1:0] digit1;
  reg [N-1:0] digit2;
  reg delay = 0;
  reg start = 0;

  spi #(.N(2*N))
    spi_1(.clk(clk),
          .mosi(mosi),
          .sck(sck),
          .ss(ss),
          .rst(rst),
          .dout(spi_out),
          .rxend(rxend)
    );

  mult #(.N(N))
    mult_1(.clk(clk),
           .din1(digit1),
           .din2(digit2),
           .start(start),
           .rst(rst),
           .dout(dout),
           .ovf(ovf),
           .ready(ready)
    );

  always @(posedge clk) begin
    if (~rst) begin
      digit1 <= 0;
      digit2 <= 0;
      delay <= 0;
      start <= 0;
    end
    else if (start) begin
      start <= 0;
    end
    else if (delay) begin
      start <= 1;
      delay <= 0;
    end
    else if (rxend) begin
      digit1 <= spi_out[N-1:0];
      digit2 <= spi_out[2*N-1:N];
      delay <= 1;
    end
  end

endmodule

tarea4/testbench/top/top_tb.v
`timescale 1ns/1ns
module top_tb();
parameter N = 8;


initial begin
  $dumpfile("top_tb.vcd");
  $dumpvars(0, top_tb);
end

reg clk;
reg rst;
reg mosi;
reg ss;
reg sck;
wire [N-1:0] dout;
wire ready;
wire ovf;

integer i;
reg [2*N-1:0] digit;

top #(.N(N))
  uut(.clk(clk),
      .rst(rst),
      .mosi(mosi),
      .ss(ss),
      .sck(sck),
      .dout(dout),
      .ready(ready),
      .ovf(ovf)
  );

initial begin
  clk = 0;
end

always #1 clk = ~clk;

initial begin

  rst = 0;
  mosi = 0;
  sck = 0;
  ss = 1;
  #10;

  rst = 1;
  #2;
  // Test 1: 7 y 15
  ss = 0;
  digit[7:0] = 8'd7;
  digit[15:8] = 8'd15;
  for (i = 0; i < 16; i = i + 1) begin
    mosi = digit[i];
    #10;
    sck = 1;
    #10;
    sck = 0;
    #10;
  end

  ss = 1;
  #10;

  // Test 2: 25 y 5
  ss = 0;
  digit[7:0] = 8'd25;
  digit[15:8] = 8'd5;
  for (i = 0; i < 16; i = i + 1) begin
    mosi = digit[i];
    #10;
    sck = 1;
    #10;
    sck = 0;
    #10;
  end

  ss = 1;
  #10;

  // Test 3: 17 y 33
  ss = 0;
  digit[7:0] = 8'd17;
  digit[15:8] = 8'd33;
  for (i = 0; i < 16; i = i + 1) begin
    mosi = digit[i];
    #10;
    sck = 1;
    #10;
    sck = 0;
    #10;
  end

  ss = 1;
  #10;

  $finish;
end

endmodule

tarea4/testbench/top/top_tb.vcd
$date
	Tue May 12 16:08:00 2020
$end
$version
	Icarus Verilog
$end
$timescale
	1ns
$end
$scope module top_tb $end
$var wire 1 ! ready $end
$var wire 1 " ovf $end
$var wire 8 # dout [7:0] $end
$var reg 1 $ clk $end
$var reg 16 % digit [15:0] $end
$var reg 1 & mosi $end
$var reg 1 ' rst $end
$var reg 1 ( sck $end
$var reg 1 ) ss $end
$var integer 32 * i [31:0] $end
$scope module uut $end
$var wire 1 $ clk $end
$var wire 1 & mosi $end
$var wire 1 ' rst $end
$var wire 1 ( sck $end
$var wire 1 ) ss $end
$var wire 16 + spi_out [15:0] $end
$var wire 1 , rxend $end
$var wire 1 ! ready $end
$var wire 1 " ovf $end
$var wire 8 - dout [7:0] $end
$var reg 1 . delay $end
$var reg 8 / digit1 [7:0] $end
$var reg 8 0 digit2 [7:0] $end
$var reg 1 1 start $end
$scope module mult_1 $end
$var wire 1 $ clk $end
$var wire 8 2 din1 [7:0] $end
$var wire 8 3 din2 [7:0] $end
$var wire 1 ' rst $end
$var wire 1 1 start $end
$var wire 1 " ovf $end
$var wire 8 4 dout [7:0] $end
$var reg 1 ! ready $end
$var reg 16 5 result [15:0] $end
$upscope $end
$scope module spi_1 $end
$var wire 1 $ clk $end
$var wire 16 6 dout [15:0] $end
$var wire 1 & mosi $end
$var wire 1 ' rst $end
$var wire 1 ( sck $end
$var wire 1 ) ss $end
$var wire 1 7 ss_rising $end
$var wire 1 8 ss_falling $end
$var wire 1 9 sck_rising $end
$var wire 1 : sck_falling $end
$var reg 16 ; counter [15:0] $end
$var reg 1 < halt $end
$var reg 1 , rxend $end
$var reg 3 = sckreg [2:0] $end
$var reg 16 > shiftreg [15:0] $end
$var reg 3 ? ssreg [2:0] $end
$upscope $end
$upscope $end
$upscope $end
$enddefinitions $end
#0
$dumpvars
bx ?
bx >
bx =
x<
bx ;
x:
x9
x8
x7
bx 6
bx 5
bx 4
bx 3
bx 2
01
bx 0
bx /
0.
bx -
x,
bx +
bx *
1)
0(
0'
0&
bx %
0$
bx #
x"
x!
$end
#1
b0 #
b0 -
b0 4
0"
bx1 ?
bx0 =
0,
b0 ;
b0 +
b0 6
b0 >
b0 5
b0 0
b0 3
b0 /
b0 2
1$
#2
0$
#3
08
09
bx11 ?
bx00 =
1$
#4
0$
#5
07
0:
b111 ?
b0 =
1$
#6
0$
#7
1$
#8
0$
#9
1$
#10
0$
1'
#11
1$
#12
0$
1&
b0 *
b111100000111 %
0)
#13
b110 ?
1$
#14
0$
#15
18
b100 ?
1$
#16
0$
#17
08
b0 ?
1$
#18
0$
#19
1$
#20
0$
#21
1$
#22
0$
1(
#23
b1 =
1$
#24
0$
#25
19
b11 =
1$
#26
0$
#27
09
b1000000000000000 +
b1000000000000000 6
b1000000000000000 >
b111 =
b1 ;
1$
#28
0$
#29
1$
#30
0$
#31
1$
#32
0$
0(
#33
b110 =
1$
#34
0$
#35
1:
b100 =
1$
#36
0$
#37
0:
b0 =
b100000000000000 +
b100000000000000 6
b100000000000000 >
1$
#38
0$
#39
1$
#40
0$
#41
1$
#42
0$
b1 *
#43
1$
#44
0$
#45
1$
#46
0$
#47
1$
#48
0$
#49
1$
#50
0$
#51
1$
#52
0$
1(
#53
b1 =
1$
#54
0$
#55
19
b11 =
1$
#56
0$
#57
09
b111 =
b1100000000000000 +
b1100000000000000 6
b1100000000000000 >
b10 ;
1$
#58
0$
#59
1$
#60
0$
#61
1$
#62
0$
0(
#63
b110 =
1$
#64
0$
#65
1:
b100 =
1$
#66
0$
#67
0:
b0 =
b110000000000000 +
b110000000000000 6
b110000000000000 >
1$
#68
0$
#69
1$
#70
0$
#71
1$
#72
0$
b10 *
#73
1$
#74
0$
#75
1$
#76
0$
#77
1$
#78
0$
#79
1$
#80
0$
#81
1$
#82
0$
1(
#83
b1 =
1$
#84
0$
#85
19
b11 =
1$
#86
0$
#87
09
b1110000000000000 +
b1110000000000000 6
b1110000000000000 >
b111 =
b11 ;
1$
#88
0$
#89
1$
#90
0$
#91
1$
#92
0$
0(
#93
b110 =
1$
#94
0$
#95
1:
b100 =
1$
#96
0$
#97
0:
b0 =
b111000000000000 +
b111000000000000 6
b111000000000000 >
1$
#98
0$
#99
1$
#100
0$
#101
1$
#102
0$
0&
b11 *
#103
1$
#104
0$
#105
1$
#106
0$
#107
1$
#108
0$
#109
1$
#110
0$
#111
1$
#112
0$
1(
#113
b1 =
1$
#114
0$
#115
19
b11 =
1$
#116
0$
#117
09
b111 =
b100 ;
1$
#118
0$
#119
1$
#120
0$
#121
1$
#122
0$
0(
#123
b110 =
1$
#124
0$
#125
1:
b100 =
1$
#126
0$
#127
0:
b0 =
b11100000000000 +
b11100000000000 6
b11100000000000 >
1$
#128
0$
#129
1$
#130
0$
#131
1$
#132
0$
b100 *
#133
1$
#134
0$
#135
1$
#136
0$
#137
1$
#138
0$
#139
1$
#140
0$
#141
1$
#142
0$
1(
#143
b1 =
1$
#144
0$
#145
19
b11 =
1$
#146
0$
#147
09
b111 =
b101 ;
1$
#148
0$
#149
1$
#150
0$
#151
1$
#152
0$
0(
#153
b110 =
1$
#154
0$
#155
1:
b100 =
1$
#156
0$
#157
0:
b0 =
b1110000000000 +
b1110000000000 6
b1110000000000 >
1$
#158
0$
#159
1$
#160
0$
#161
1$
#162
0$
b101 *
#163
1$
#164
0$
#165
1$
#166
0$
#167
1$
#168
0$
#169
1$
#170
0$
#171
1$
#172
0$
1(
#173
b1 =
1$
#174
0$
#175
19
b11 =
1$
#176
0$
#177
09
b111 =
b110 ;
1$
#178
0$
#179
1$
#180
0$
#181
1$
#182
0$
0(
#183
b110 =
1$
#184
0$
#185
1:
b100 =
1$
#186
0$
#187
0:
b0 =
b111000000000 +
b111000000000 6
b111000000000 >
1$
#188
0$
#189
1$
#190
0$
#191
1$
#192
0$
b110 *
#193
1$
#194
0$
#195
1$
#196
0$
#197
1$
#198
0$
#199
1$
#200
0$
#201
1$
#202
0$
1(
#203
b1 =
1$
#204
0$
#205
19
b11 =
1$
#206
0$
#207
09
b111 =
b111 ;
1$
#208
0$
#209
1$
#210
0$
#211
1$
#212
0$
0(
#213
b110 =
1$
#214
0$
#215
1:
b100 =
1$
#216
0$
#217
0:
b0 =
b11100000000 +
b11100000000 6
b11100000000 >
1$
#218
0$
#219
1$
#220
0$
#221
1$
#222
0$
b111 *
#223
1$
#224
0$
#225
1$
#226
0$
#227
1$
#228
0$
#229
1$
#230
0$
#231
1$
#232
0$
1(
#233
b1 =
1$
#234
0$
#235
19
b11 =
1$
#236
0$
#237
09
b111 =
b1000 ;
1$
#238
0$
#239
1$
#240
0$
#241
1$
#242
0$
0(
#243
b110 =
1$
#244
0$
#245
1:
b100 =
1$
#246
0$
#247
0:
b0 =
b1110000000 +
b1110000000 6
b1110000000 >
1$
#248
0$
#249
1$
#250
0$
#251
1$
#252
0$
1&
b1000 *
#253
1$
#254
0$
#255
1$
#256
0$
#257
1$
#258
0$
#259
1$
#260
0$
#261
1$
#262
0$
1(
#263
b1 =
1$
#264
0$
#265
19
b11 =
1$
#266
0$
#267
09
b1000001110000000 +
b1000001110000000 6
b1000001110000000 >
b111 =
b1001 ;
1$
#268
0$
#269
1$
#270
0$
#271
1$
#272
0$
0(
#273
b110 =
1$
#274
0$
#275
1:
b100 =
1$
#276
0$
#277
0:
b0 =
b100000111000000 +
b100000111000000 6
b100000111000000 >
1$
#278
0$
#279
1$
#280
0$
#281
1$
#282
0$
b1001 *
#283
1$
#284
0$
#285
1$
#286
0$
#287
1$
#288
0$
#289
1$
#290
0$
#291
1$
#292
0$
1(
#293
b1 =
1$
#294
0$
#295
19
b11 =
1$
#296
0$
#297
09
b111 =
b1100000111000000 +
b1100000111000000 6
b1100000111000000 >
b1010 ;
1$
#298
0$
#299
1$
#300
0$
#301
1$
#302
0$
0(
#303
b110 =
1$
#304
0$
#305
1:
b100 =
1$
#306
0$
#307
0:
b0 =
b110000011100000 +
b110000011100000 6
b110000011100000 >
1$
#308
0$
#309
1$
#310
0$
#311
1$
#312
0$
b1010 *
#313
1$
#314
0$
#315
1$
#316
0$
#317
1$
#318
0$
#319
1$
#320
0$
#321
1$
#322
0$
1(
#323
b1 =
1$
#324
0$
#325
19
b11 =
1$
#326
0$
#327
09
b1110000011100000 +
b1110000011100000 6
b1110000011100000 >
b111 =
b1011 ;
1$
#328
0$
#329
1$
#330
0$
#331
1$
#332
0$
0(
#333
b110 =
1$
#334
0$
#335
1:
b100 =
1$
#336
0$
#337
0:
b0 =
b111000001110000 +
b111000001110000 6
b111000001110000 >
1$
#338
0$
#339
1$
#340
0$
#341
1$
#342
0$
b1011 *
#343
1$
#344
0$
#345
1$
#346
0$
#347
1$
#348
0$
#349
1$
#350
0$
#351
1$
#352
0$
1(
#353
b1 =
1$
#354
0$
#355
19
b11 =
1$
#356
0$
#357
09
b111 =
b1111000001110000 +
b1111000001110000 6
b1111000001110000 >
b1100 ;
1$
#358
0$
#359
1$
#360
0$
#361
1$
#362
0$
0(
#363
b110 =
1$
#364
0$
#365
1:
b100 =
1$
#366
0$
#367
0:
b0 =
b111100000111000 +
b111100000111000 6
b111100000111000 >
1$
#368
0$
#369
1$
#370
0$
#371
1$
#372
0$
0&
b1100 *
#373
1$
#374
0$
#375
1$
#376
0$
#377
1$
#378
0$
#379
1$
#380
0$
#381
1$
#382
0$
1(
#383
b1 =
1$
#384
0$
#385
19
b11 =
1$
#386
0$
#387
09
b111 =
b1101 ;
1$
#388
0$
#389
1$
#390
0$
#391
1$
#392
0$
0(
#393
b110 =
1$
#394
0$
#395
1:
b100 =
1$
#396
0$
#397
0:
b0 =
b11110000011100 +
b11110000011100 6
b11110000011100 >
1$
#398
0$
#399
1$
#400
0$
#401
1$
#402
0$
b1101 *
#403
1$
#404
0$
#405
1$
#406
0$
#407
1$
#408
0$
#409
1$
#410
0$
#411
1$
#412
0$
1(
#413
b1 =
1$
#414
0$
#415
19
b11 =
1$
#416
0$
#417
09
b111 =
b1110 ;
1$
#418
0$
#419
1$
#420
0$
#421
1$
#422
0$
0(
#423
b110 =
1$
#424
0$
#425
1:
b100 =
1$
#426
0$
#427
0:
b0 =
b1111000001110 +
b1111000001110 6
b1111000001110 >
1$
#428
0$
#429
1$
#430
0$
#431
1$
#432
0$
b1110 *
#433
1$
#434
0$
#435
1$
#436
0$
#437
1$
#438
0$
#439
1$
#440
0$
#441
1$
#442
0$
1(
#443
b1 =
1$
#444
0$
#445
19
b11 =
1$
#446
0$
#447
09
b111 =
b1111 ;
1$
#448
0$
#449
1$
#450
0$
#451
1$
#452
0$
0(
#453
b110 =
1$
#454
0$
#455
1:
b100 =
1$
#456
0$
#457
0:
b0 =
b111100000111 +
b111100000111 6
b111100000111 >
1$
#458
0$
#459
1$
#460
0$
#461
1$
#462
0$
b1111 *
#463
1$
#464
0$
#465
1$
#466
0$
#467
1$
#468
0$
#469
1$
#470
0$
#471
1$
#472
0$
1(
#473
b1 =
1$
#474
0$
#475
19
b11 =
1$
#476
0$
#477
09
b111 =
b10000 ;
1$
#478
0$
#479
1$
#480
0$
#481
1$
#482
0$
0(
#483
b110 =
1$
#484
0$
#485
1:
b100 =
1$
#486
0$
#487
0:
1,
1<
b0 =
1$
#488
0$
#489
0,
1.
b1111 0
b1111 3
b111 /
b111 2
1$
#490
0$
#491
0.
11
1$
#492
0$
1)
b10000 *
#493
b1101001 #
b1101001 -
b1101001 4
b1 ?
1!
b1101001 5
01
1$
#494
0$
#495
17
0!
b11 ?
1$
#496
0$
#497
07
b111 ?
1$
#498
0$
#499
1$
#500
0$
#501
1$
#502
0$
1&
b0 *
b10100011001 %
0)
#503
b110 ?
1$
#504
0$
#505
18
b100 ?
1$
#506
0$
#507
08
0<
b0 ;
b0 +
b0 6
b0 >
b0 ?
1$
#508
0$
#509
1$
#510
0$
#511
1$
#512
0$
1(
#513
b1 =
1$
#514
0$
#515
19
b11 =
1$
#516
0$
#517
09
b111 =
b1000000000000000 +
b1000000000000000 6
b1000000000000000 >
b1 ;
1$
#518
0$
#519
1$
#520
0$
#521
1$
#522
0$
0(
#523
b110 =
1$
#524
0$
#525
1:
b100 =
1$
#526
0$
#527
0:
b0 =
b100000000000000 +
b100000000000000 6
b100000000000000 >
1$
#528
0$
#529
1$
#530
0$
#531
1$
#532
0$
0&
b1 *
#533
1$
#534
0$
#535
1$
#536
0$
#537
1$
#538
0$
#539
1$
#540
0$
#541
1$
#542
0$
1(
#543
b1 =
1$
#544
0$
#545
19
b11 =
1$
#546
0$
#547
09
b111 =
b10 ;
1$
#548
0$
#549
1$
#550
0$
#551
1$
#552
0$
0(
#553
b110 =
1$
#554
0$
#555
1:
b100 =
1$
#556
0$
#557
0:
b0 =
b10000000000000 +
b10000000000000 6
b10000000000000 >
1$
#558
0$
#559
1$
#560
0$
#561
1$
#562
0$
b10 *
#563
1$
#564
0$
#565
1$
#566
0$
#567
1$
#568
0$
#569
1$
#570
0$
#571
1$
#572
0$
1(
#573
b1 =
1$
#574
0$
#575
19
b11 =
1$
#576
0$
#577
09
b111 =
b11 ;
1$
#578
0$
#579
1$
#580
0$
#581
1$
#582
0$
0(
#583
b110 =
1$
#584
0$
#585
1:
b100 =
1$
#586
0$
#587
0:
b0 =
b1000000000000 +
b1000000000000 6
b1000000000000 >
1$
#588
0$
#589
1$
#590
0$
#591
1$
#592
0$
1&
b11 *
#593
1$
#594
0$
#595
1$
#596
0$
#597
1$
#598
0$
#599
1$
#600
0$
#601
1$
#602
0$
1(
#603
b1 =
1$
#604
0$
#605
19
b11 =
1$
#606
0$
#607
09
b1001000000000000 +
b1001000000000000 6
b1001000000000000 >
b111 =
b100 ;
1$
#608
0$
#609
1$
#610
0$
#611
1$
#612
0$
0(
#613
b110 =
1$
#614
0$
#615
1:
b100 =
1$
#616
0$
#617
0:
b0 =
b100100000000000 +
b100100000000000 6
b100100000000000 >
1$
#618
0$
#619
1$
#620
0$
#621
1$
#622
0$
b100 *
#623
1$
#624
0$
#625
1$
#626
0$
#627
1$
#628
0$
#629
1$
#630
0$
#631
1$
#632
0$
1(
#633
b1 =
1$
#634
0$
#635
19
b11 =
1$
#636
0$
#637
09
b111 =
b1100100000000000 +
b1100100000000000 6
b1100100000000000 >
b101 ;
1$
#638
0$
#639
1$
#640
0$
#641
1$
#642
0$
0(
#643
b110 =
1$
#644
0$
#645
1:
b100 =
1$
#646
0$
#647
0:
b0 =
b110010000000000 +
b110010000000000 6
b110010000000000 >
1$
#648
0$
#649
1$
#650
0$
#651
1$
#652
0$
0&
b101 *
#653
1$
#654
0$
#655
1$
#656
0$
#657
1$
#658
0$
#659
1$
#660
0$
#661
1$
#662
0$
1(
#663
b1 =
1$
#664
0$
#665
19
b11 =
1$
#666
0$
#667
09
b111 =
b110 ;
1$
#668
0$
#669
1$
#670
0$
#671
1$
#672
0$
0(
#673
b110 =
1$
#674
0$
#675
1:
b100 =
1$
#676
0$
#677
0:
b0 =
b11001000000000 +
b11001000000000 6
b11001000000000 >
1$
#678
0$
#679
1$
#680
0$
#681
1$
#682
0$
b110 *
#683
1$
#684
0$
#685
1$
#686
0$
#687
1$
#688
0$
#689
1$
#690
0$
#691
1$
#692
0$
1(
#693
b1 =
1$
#694
0$
#695
19
b11 =
1$
#696
0$
#697
09
b111 =
b111 ;
1$
#698
0$
#699
1$
#700
0$
#701
1$
#702
0$
0(
#703
b110 =
1$
#704
0$
#705
1:
b100 =
1$
#706
0$
#707
0:
b0 =
b1100100000000 +
b1100100000000 6
b1100100000000 >
1$
#708
0$
#709
1$
#710
0$
#711
1$
#712
0$
b111 *
#713
1$
#714
0$
#715
1$
#716
0$
#717
1$
#718
0$
#719
1$
#720
0$
#721
1$
#722
0$
1(
#723
b1 =
1$
#724
0$
#725
19
b11 =
1$
#726
0$
#727
09
b111 =
b1000 ;
1$
#728
0$
#729
1$
#730
0$
#731
1$
#732
0$
0(
#733
b110 =
1$
#734
0$
#735
1:
b100 =
1$
#736
0$
#737
0:
b0 =
b110010000000 +
b110010000000 6
b110010000000 >
1$
#738
0$
#739
1$
#740
0$
#741
1$
#742
0$
1&
b1000 *
#743
1$
#744
0$
#745
1$
#746
0$
#747
1$
#748
0$
#749
1$
#750
0$
#751
1$
#752
0$
1(
#753
b1 =
1$
#754
0$
#755
19
b11 =
1$
#756
0$
#757
09
b111 =
b1000110010000000 +
b1000110010000000 6
b1000110010000000 >
b1001 ;
1$
#758
0$
#759
1$
#760
0$
#761
1$
#762
0$
0(
#763
b110 =
1$
#764
0$
#765
1:
b100 =
1$
#766
0$
#767
0:
b0 =
b100011001000000 +
b100011001000000 6
b100011001000000 >
1$
#768
0$
#769
1$
#770
0$
#771
1$
#772
0$
0&
b1001 *
#773
1$
#774
0$
#775
1$
#776
0$
#777
1$
#778
0$
#779
1$
#780
0$
#781
1$
#782
0$
1(
#783
b1 =
1$
#784
0$
#785
19
b11 =
1$
#786
0$
#787
09
b111 =
b1010 ;
1$
#788
0$
#789
1$
#790
0$
#791
1$
#792
0$
0(
#793
b110 =
1$
#794
0$
#795
1:
b100 =
1$
#796
0$
#797
0:
b0 =
b10001100100000 +
b10001100100000 6
b10001100100000 >
1$
#798
0$
#799
1$
#800
0$
#801
1$
#802
0$
1&
b1010 *
#803
1$
#804
0$
#805
1$
#806
0$
#807
1$
#808
0$
#809
1$
#810
0$
#811
1$
#812
0$
1(
#813
b1 =
1$
#814
0$
#815
19
b11 =
1$
#816
0$
#817
09
b111 =
b1010001100100000 +
b1010001100100000 6
b1010001100100000 >
b1011 ;
1$
#818
0$
#819
1$
#820
0$
#821
1$
#822
0$
0(
#823
b110 =
1$
#824
0$
#825
1:
b100 =
1$
#826
0$
#827
0:
b0 =
b101000110010000 +
b101000110010000 6
b101000110010000 >
1$
#828
0$
#829
1$
#830
0$
#831
1$
#832
0$
0&
b1011 *
#833
1$
#834
0$
#835
1$
#836
0$
#837
1$
#838
0$
#839
1$
#840
0$
#841
1$
#842
0$
1(
#843
b1 =
1$
#844
0$
#845
19
b11 =
1$
#846
0$
#847
09
b111 =
b1100 ;
1$
#848
0$
#849
1$
#850
0$
#851
1$
#852
0$
0(
#853
b110 =
1$
#854
0$
#855
1:
b100 =
1$
#856
0$
#857
0:
b0 =
b10100011001000 +
b10100011001000 6
b10100011001000 >
1$
#858
0$
#859
1$
#860
0$
#861
1$
#862
0$
b1100 *
#863
1$
#864
0$
#865
1$
#866
0$
#867
1$
#868
0$
#869
1$
#870
0$
#871
1$
#872
0$
1(
#873
b1 =
1$
#874
0$
#875
19
b11 =
1$
#876
0$
#877
09
b111 =
b1101 ;
1$
#878
0$
#879
1$
#880
0$
#881
1$
#882
0$
0(
#883
b110 =
1$
#884
0$
#885
1:
b100 =
1$
#886
0$
#887
0:
b0 =
b1010001100100 +
b1010001100100 6
b1010001100100 >
1$
#888
0$
#889
1$
#890
0$
#891
1$
#892
0$
b1101 *
#893
1$
#894
0$
#895
1$
#896
0$
#897
1$
#898
0$
#899
1$
#900
0$
#901
1$
#902
0$
1(
#903
b1 =
1$
#904
0$
#905
19
b11 =
1$
#906
0$
#907
09
b111 =
b1110 ;
1$
#908
0$
#909
1$
#910
0$
#911
1$
#912
0$
0(
#913
b110 =
1$
#914
0$
#915
1:
b100 =
1$
#916
0$
#917
0:
b0 =
b101000110010 +
b101000110010 6
b101000110010 >
1$
#918
0$
#919
1$
#920
0$
#921
1$
#922
0$
b1110 *
#923
1$
#924
0$
#925
1$
#926
0$
#927
1$
#928
0$
#929
1$
#930
0$
#931
1$
#932
0$
1(
#933
b1 =
1$
#934
0$
#935
19
b11 =
1$
#936
0$
#937
09
b111 =
b1111 ;
1$
#938
0$
#939
1$
#940
0$
#941
1$
#942
0$
0(
#943
b110 =
1$
#944
0$
#945
1:
b100 =
1$
#946
0$
#947
0:
b0 =
b10100011001 +
b10100011001 6
b10100011001 >
1$
#948
0$
#949
1$
#950
0$
#951
1$
#952
0$
b1111 *
#953
1$
#954
0$
#955
1$
#956
0$
#957
1$
#958
0$
#959
1$
#960
0$
#961
1$
#962
0$
1(
#963
b1 =
1$
#964
0$
#965
19
b11 =
1$
#966
0$
#967
09
b111 =
b10000 ;
1$
#968
0$
#969
1$
#970
0$
#971
1$
#972
0$
0(
#973
b110 =
1$
#974
0$
#975
1:
b100 =
1$
#976
0$
#977
0:
b0 =
1,
1<
1$
#978
0$
#979
1.
b101 0
b101 3
b11001 /
b11001 2
0,
1$
#980
0$
#981
0.
11
1$
#982
0$
1)
b10000 *
#983
b1111101 #
b1111101 -
b1111101 4
01
1!
b1111101 5
b1 ?
1$
#984
0$
#985
17
b11 ?
0!
1$
#986
0$
#987
07
b111 ?
1$
#988
0$
#989
1$
#990
0$
#991
1$
#992
0$
1&
b0 *
b10000100010001 %
0)
#993
b110 ?
1$
#994
0$
#995
18
b100 ?
1$
#996
0$
#997
08
b0 ?
0<
b0 ;
b0 +
b0 6
b0 >
1$
#998
0$
#999
1$
#1000
0$
#1001
1$
#1002
0$
1(
#1003
b1 =
1$
#1004
0$
#1005
19
b11 =
1$
#1006
0$
#1007
09
b1000000000000000 +
b1000000000000000 6
b1000000000000000 >
b111 =
b1 ;
1$
#1008
0$
#1009
1$
#1010
0$
#1011
1$
#1012
0$
0(
#1013
b110 =
1$
#1014
0$
#1015
1:
b100 =
1$
#1016
0$
#1017
0:
b0 =
b100000000000000 +
b100000000000000 6
b100000000000000 >
1$
#1018
0$
#1019
1$
#1020
0$
#1021
1$
#1022
0$
0&
b1 *
#1023
1$
#1024
0$
#1025
1$
#1026
0$
#1027
1$
#1028
0$
#1029
1$
#1030
0$
#1031
1$
#1032
0$
1(
#1033
b1 =
1$
#1034
0$
#1035
19
b11 =
1$
#1036
0$
#1037
09
b111 =
b10 ;
1$
#1038
0$
#1039
1$
#1040
0$
#1041
1$
#1042
0$
0(
#1043
b110 =
1$
#1044
0$
#1045
1:
b100 =
1$
#1046
0$
#1047
0:
b0 =
b10000000000000 +
b10000000000000 6
b10000000000000 >
1$
#1048
0$
#1049
1$
#1050
0$
#1051
1$
#1052
0$
b10 *
#1053
1$
#1054
0$
#1055
1$
#1056
0$
#1057
1$
#1058
0$
#1059
1$
#1060
0$
#1061
1$
#1062
0$
1(
#1063
b1 =
1$
#1064
0$
#1065
19
b11 =
1$
#1066
0$
#1067
09
b111 =
b11 ;
1$
#1068
0$
#1069
1$
#1070
0$
#1071
1$
#1072
0$
0(
#1073
b110 =
1$
#1074
0$
#1075
1:
b100 =
1$
#1076
0$
#1077
0:
b0 =
b1000000000000 +
b1000000000000 6
b1000000000000 >
1$
#1078
0$
#1079
1$
#1080
0$
#1081
1$
#1082
0$
b11 *
#1083
1$
#1084
0$
#1085
1$
#1086
0$
#1087
1$
#1088
0$
#1089
1$
#1090
0$
#1091
1$
#1092
0$
1(
#1093
b1 =
1$
#1094
0$
#1095
19
b11 =
1$
#1096
0$
#1097
09
b111 =
b100 ;
1$
#1098
0$
#1099
1$
#1100
0$
#1101
1$
#1102
0$
0(
#1103
b110 =
1$
#1104
0$
#1105
1:
b100 =
1$
#1106
0$
#1107
0:
b0 =
b100000000000 +
b100000000000 6
b100000000000 >
1$
#1108
0$
#1109
1$
#1110
0$
#1111
1$
#1112
0$
1&
b100 *
#1113
1$
#1114
0$
#1115
1$
#1116
0$
#1117
1$
#1118
0$
#1119
1$
#1120
0$
#1121
1$
#1122
0$
1(
#1123
b1 =
1$
#1124
0$
#1125
19
b11 =
1$
#1126
0$
#1127
09
b1000100000000000 +
b1000100000000000 6
b1000100000000000 >
b111 =
b101 ;
1$
#1128
0$
#1129
1$
#1130
0$
#1131
1$
#1132
0$
0(
#1133
b110 =
1$
#1134
0$
#1135
1:
b100 =
1$
#1136
0$
#1137
0:
b0 =
b100010000000000 +
b100010000000000 6
b100010000000000 >
1$
#1138
0$
#1139
1$
#1140
0$
#1141
1$
#1142
0$
0&
b101 *
#1143
1$
#1144
0$
#1145
1$
#1146
0$
#1147
1$
#1148
0$
#1149
1$
#1150
0$
#1151
1$
#1152
0$
1(
#1153
b1 =
1$
#1154
0$
#1155
19
b11 =
1$
#1156
0$
#1157
09
b111 =
b110 ;
1$
#1158
0$
#1159
1$
#1160
0$
#1161
1$
#1162
0$
0(
#1163
b110 =
1$
#1164
0$
#1165
1:
b100 =
1$
#1166
0$
#1167
0:
b0 =
b10001000000000 +
b10001000000000 6
b10001000000000 >
1$
#1168
0$
#1169
1$
#1170
0$
#1171
1$
#1172
0$
b110 *
#1173
1$
#1174
0$
#1175
1$
#1176
0$
#1177
1$
#1178
0$
#1179
1$
#1180
0$
#1181
1$
#1182
0$
1(
#1183
b1 =
1$
#1184
0$
#1185
19
b11 =
1$
#1186
0$
#1187
09
b111 =
b111 ;
1$
#1188
0$
