tarea4/rtl/mult.v
module mult(clk, din1, din2, start, rst, dout, ovf, ready);
  parameter N = 8;
  input clk;
  input [N-1:0] din1;
  input [N-1:0] din2;
  input start;
  input rst;
  output [N-1:0] dout;
  output ovf;
  output reg ready;

  reg [2*N-1:0] result;

  always @(posedge clk or rst) begin
    if (~rst) begin
      result <= 0;
    end
    else if (ready) begin
      ready <= 0;
    end
    else if (start) begin
      result <= din1 * din2;
      ready <= 1;
    end
  end

  // Outputs
  assign ovf = result[2*N-1:N] > 0;
  assign dout = ovf ? {N{1'b1}} : result[N-1:0];

  endmodule

tarea4/rtl/spi.v
// https://www.fpga4fun.com/SPI2.html
// N bits SPI receiver, Mode 0.
//
// ss = 1;
// #10
// Reception doesn't end until N bits are received. This enables receiving
// separate bytes.
// Once reception ended, rxend will set for one clock cycle.
module spi(clk, mosi, sck, ss, rst, dout, rxend);
  parameter N = 16;
  input clk;
  input mosi;
  input sck;
  input ss;
  input rst;
  output [N-1:0] dout;
  output reg rxend;

  reg [N-1:0] shiftreg;
  reg [N-1:0] counter;
  reg [2:0] sckreg;
  reg [2:0] ssreg;
  reg halt;
  wire sck_rising;
  wire ss_rising;
  wire ss_falling;

  // Sync with clk
  always @(posedge clk) begin
    sckreg <= {sckreg[1:0], sck};
    ssreg  <= {ssreg[1:0], ss};
  end

  assign sck_rising  = (sckreg[2:1] == 2'b01);
  assign sck_falling = (sckreg[2:1] == 2'b10);
  assign ss_rising   = (ssreg[2:1] == 2'b01);
  assign ss_falling  = (ssreg[2:1] == 2'b10);

  // Main
  always @(posedge clk) begin
    if (~rst) begin
      shiftreg <= 0;
      counter <= 0;
      rxend <= 0;
    end
    // Receiving mode
    else if (!ss) begin
      // RX starting
      if (ss_falling & halt) begin
        shiftreg <= 0;
        counter <= 0;
        rxend <= 0;
        halt <= 0;
      end
      // RX ended
      else if (halt) begin
        rxend <= 0; // Reset rxend
      end
      // Sample bit
      else if (sck_rising) begin
        shiftreg[N-1] <= mosi;
        counter = counter + 1;
      end
      // Shift
      else if (sck_falling) begin
        if (counter == N) begin
          halt <= 1;
          rxend <= 1;
        end
        else begin
          shiftreg = shiftreg >> 1;
        end
      end
    end

    // IDLE mode
    else if (ss) begin
      // RX ended
      if (halt) begin
        rxend <= 0; // Reset rxend
      end
      if (ss_rising) begin
      end
    end
  end

assign dout = shiftreg;


endmodule

tarea4/rtl/top.v
module top(clk, rst, mosi, ss, sck, dout, ready, ovf);
  parameter N = 8;
  input clk;
  input rst;
  input mosi;
  input ss;
  input sck;
  output [N-1:0] dout;
  output ready;
  output ovf;

  wire [2*N-1:0] spi_out;
  wire rxend;
  reg [N-1:0] digit1 = 0;
  reg [N-1:0] digit2 = 0;
  reg delay = 0;
  reg start = 0;

  spi #(.N(2*N))
    spi_1(.clk(clk),
          .mosi(mosi),
          .sck(sck),
          .ss(ss),
          .rst(rst),
          .dout(spi_out),
          .rxend(rxend)
    );

  mult #(.N(N))
    mult_1(.clk(clk),
           .din1(digit1),
           .din2(digit2),
           .start(start),
           .rst(rst),
           .dout(dout),
           .ovf(ovf),
           .ready(ready)
    );

  always @(posedge clk) begin
    if (rst) begin
      digit1 <= 0;
      digit2 <= 0;
      delay <= 0;
      start <= 0;
    end
    if (rxend) begin
      digit1 <= spi_out[N-1:0];
      digit2 <= spi_out[2*N-1:N];
      delay <= 1;
    end
    else if (delay) begin
      start <= 1;
      delay <= 0;
    end
    else if (start) begin
      start <= 0;
    end
  end

endmodule

tarea4/testbench/top/top_tb.v
`timescale 1ns/1ns
module top_tb();
parameter N = 8;


initial begin
  $dumpfile("top_tb.vcd");
  $dumpvars(0, top_tb);
end

reg clk;
reg rst;
reg mosi;
reg ss;
reg sck;
wire [N-1:0] dout;
wire ready;
wire ovf;

integer i;
reg [2*N-1:0] digit;

top #(.N(N))
  uut(.clk(clk),
      .rst(rst),
      .mosi(mosi),
      .ss(ss),
      .sck(sck),
      .dout(dout),
      .ready(ready),
      .ovf(ovf)
  );

initial begin
  clk = 0;
end

always #1 clk = ~clk;

initial begin

  rst = 0;
  mosi = 0;
  sck = 0;
  ss = 1;
  #6;

  rst = 1;
  #2;
  // Test 1: 7 y 15
  ss = 0;
  digit[7:0] = 8'd7;
  digit[15:8] = 8'd15;
  for (i = 0; i < 16; i = i + 1) begin
    mosi = digit[i];
    #10;
    sck = 1;
    #10;
    sck = 0;
    #10;
  end

  ss = 1;
  #10;

  // Test 2: 25 y 5
  ss = 0;
  digit[7:0] = 8'd25;
  digit[15:8] = 8'd5;
  for (i = 0; i < 16; i = i + 1) begin
    mosi = digit[i];
    #10;
    sck = 1;
    #10;
    sck = 0;
    #10;
  end

  ss = 1;
  #10;

  // Test 3: 17 y 33
  ss = 0;
  digit[7:0] = 8'd17;
  digit[15:8] = 8'd33;
  for (i = 0; i < 16; i = i + 1) begin
    mosi = digit[i];
    #10;
    sck = 1;
    #10;
    sck = 0;
    #10;
  end

  ss = 1;
  #10;

  $finish;
end

endmodule

tarea4/testbench/top/top_tb.vcd
$date
	Tue May 12 00:54:28 2020
$end
$version
	Icarus Verilog
$end
$timescale
	1ns
$end
$scope module top_tb $end
$var wire 1 ! ready $end
$var wire 1 " ovf $end
$var wire 8 # dout [7:0] $end
$var reg 1 $ clk $end
$var reg 16 % digit [15:0] $end
$var reg 1 & mosi $end
$var reg 1 ' rst $end
$var reg 1 ( sck $end
$var reg 1 ) ss $end
$var integer 32 * i [31:0] $end
$scope module uut $end
$var wire 1 $ clk $end
$var wire 1 & mosi $end
$var wire 1 ' rst $end
$var wire 1 ( sck $end
$var wire 1 ) ss $end
$var wire 16 + spi_out [15:0] $end
$var wire 1 , rxend $end
$var wire 1 ! ready $end
$var wire 1 " ovf $end
$var wire 8 - dout [7:0] $end
$var reg 1 . delay $end
$var reg 8 / digit1 [7:0] $end
$var reg 8 0 digit2 [7:0] $end
$var reg 1 1 start $end
$scope module mult_1 $end
$var wire 1 $ clk $end
$var wire 8 2 din1 [7:0] $end
$var wire 8 3 din2 [7:0] $end
$var wire 1 ' rst $end
$var wire 1 1 start $end
$var wire 1 " ovf $end
$var wire 8 4 dout [7:0] $end
$var reg 1 ! ready $end
$var reg 16 5 result [15:0] $end
$upscope $end
$scope module spi_1 $end
$var wire 1 $ clk $end
$var wire 16 6 dout [15:0] $end
$var wire 1 & mosi $end
$var wire 1 ' rst $end
$var wire 1 ( sck $end
$var wire 1 ) ss $end
$var wire 1 7 ss_rising $end
$var wire 1 8 ss_falling $end
$var wire 1 9 sck_rising $end
$var wire 1 : sck_falling $end
$var reg 16 ; counter [15:0] $end
$var reg 1 < halt $end
$var reg 1 , rxend $end
$var reg 3 = sckreg [2:0] $end
$var reg 16 > shiftreg [15:0] $end
$var reg 3 ? ssreg [2:0] $end
$upscope $end
$upscope $end
$upscope $end
$enddefinitions $end
#0
$dumpvars
bx ?
bx >
bx =
x<
bx ;
x:
x9
x8
x7
bx 6
b0 5
b0 4
b0 3
b0 2
01
b0 0
b0 /
0.
b0 -
x,
bx +
bx *
1)
0(
0'
0&
bx %
0$
b0 #
0"
x!
$end
#1
bx1 ?
bx0 =
0,
b0 ;
b0 +
b0 6
b0 >
1$
#2
0$
#3
08
09
bx11 ?
bx00 =
1$
#4
0$
#5
07
0:
b111 ?
b0 =
1$
#6
0$
1'
#7
1$
#8
0$
1&
b0 *
b111100000111 %
0)
#9
b110 ?
1$
#10
0$
#11
18
b100 ?
1$
#12
0$
#13
08
b0 ?
1$
#14
0$
#15
1$
#16
0$
#17
1$
#18
0$
1(
#19
b1 =
1$
#20
0$
#21
19
b11 =
1$
#22
0$
#23
09
b1000000000000000 +
b1000000000000000 6
b1000000000000000 >
b111 =
b1 ;
1$
#24
0$
#25
1$
#26
0$
#27
1$
#28
0$
0(
#29
b110 =
1$
#30
0$
#31
1:
b100 =
1$
#32
0$
#33
0:
b0 =
b100000000000000 +
b100000000000000 6
b100000000000000 >
1$
#34
0$
#35
1$
#36
0$
#37
1$
#38
0$
b1 *
#39
1$
#40
0$
#41
1$
#42
0$
#43
1$
#44
0$
#45
1$
#46
0$
#47
1$
#48
0$
1(
#49
b1 =
1$
#50
0$
#51
19
b11 =
1$
#52
0$
#53
09
b111 =
b1100000000000000 +
b1100000000000000 6
b1100000000000000 >
b10 ;
1$
#54
0$
#55
1$
#56
0$
#57
1$
#58
0$
0(
#59
b110 =
1$
#60
0$
#61
1:
b100 =
1$
#62
0$
#63
0:
b0 =
b110000000000000 +
b110000000000000 6
b110000000000000 >
1$
#64
0$
#65
1$
#66
0$
#67
1$
#68
0$
b10 *
#69
1$
#70
0$
#71
1$
#72
0$
#73
1$
#74
0$
#75
1$
#76
0$
#77
1$
#78
0$
1(
#79
b1 =
1$
#80
0$
#81
19
b11 =
1$
#82
0$
#83
09
b1110000000000000 +
b1110000000000000 6
b1110000000000000 >
b111 =
b11 ;
1$
#84
0$
#85
1$
#86
0$
#87
1$
#88
0$
0(
#89
b110 =
1$
#90
0$
#91
1:
b100 =
1$
#92
0$
#93
0:
b0 =
b111000000000000 +
b111000000000000 6
b111000000000000 >
1$
#94
0$
#95
1$
#96
0$
#97
1$
#98
0$
0&
b11 *
#99
1$
#100
0$
#101
1$
#102
0$
#103
1$
#104
0$
#105
1$
#106
0$
#107
1$
#108
0$
1(
#109
b1 =
1$
#110
0$
#111
19
b11 =
1$
#112
0$
#113
09
b111 =
b100 ;
1$
#114
0$
#115
1$
#116
0$
#117
1$
#118
0$
0(
#119
b110 =
1$
#120
0$
#121
1:
b100 =
1$
#122
0$
#123
0:
b0 =
b11100000000000 +
b11100000000000 6
b11100000000000 >
1$
#124
0$
#125
1$
#126
0$
#127
1$
#128
0$
b100 *
#129
1$
#130
0$
#131
1$
#132
0$
#133
1$
#134
0$
#135
1$
#136
0$
#137
1$
#138
0$
1(
#139
b1 =
1$
#140
0$
#141
19
b11 =
1$
#142
0$
#143
09
b111 =
b101 ;
1$
#144
0$
#145
1$
#146
0$
#147
1$
#148
0$
0(
#149
b110 =
1$
#150
0$
#151
1:
b100 =
1$
#152
0$
#153
0:
b0 =
b1110000000000 +
b1110000000000 6
b1110000000000 >
1$
#154
0$
#155
1$
#156
0$
#157
1$
#158
0$
b101 *
#159
1$
#160
0$
#161
1$
#162
0$
#163
1$
#164
0$
#165
1$
#166
0$
#167
1$
#168
0$
1(
#169
b1 =
1$
#170
0$
#171
19
b11 =
1$
#172
0$
#173
09
b111 =
b110 ;
1$
#174
0$
#175
1$
#176
0$
#177
1$
#178
0$
0(
#179
b110 =
1$
#180
0$
#181
1:
b100 =
1$
#182
0$
#183
0:
b0 =
b111000000000 +
b111000000000 6
b111000000000 >
1$
#184
0$
#185
1$
#186
0$
#187
1$
#188
0$
b110 *
#189
1$
#190
0$
#191
1$
#192
0$
#193
1$
#194
0$
#195
1$
#196
0$
#197
1$
#198
0$
1(
#199
b1 =
1$
#200
0$
#201
19
b11 =
1$
#202
0$
#203
09
b111 =
b111 ;
1$
#204
0$
#205
1$
#206
0$
#207
1$
#208
0$
0(
#209
b110 =
1$
#210
0$
#211
1:
b100 =
1$
#212
0$
#213
0:
b0 =
b11100000000 +
b11100000000 6
b11100000000 >
1$
#214
0$
#215
1$
#216
0$
#217
1$
#218
0$
b111 *
#219
1$
#220
0$
#221
1$
#222
0$
#223
1$
#224
0$
#225
1$
#226
0$
#227
1$
#228
0$
1(
#229
b1 =
1$
#230
0$
#231
19
b11 =
1$
#232
0$
#233
09
b111 =
b1000 ;
1$
#234
0$
#235
1$
#236
0$
#237
1$
#238
0$
0(
#239
b110 =
1$
#240
0$
#241
1:
b100 =
1$
#242
0$
#243
0:
b0 =
b1110000000 +
b1110000000 6
b1110000000 >
1$
#244
0$
#245
1$
#246
0$
#247
1$
#248
0$
1&
b1000 *
#249
1$
#250
0$
#251
1$
#252
0$
#253
1$
#254
0$
#255
1$
#256
0$
#257
1$
#258
0$
1(
#259
b1 =
1$
#260
0$
#261
19
b11 =
1$
#262
0$
#263
09
b1000001110000000 +
b1000001110000000 6
b1000001110000000 >
b111 =
b1001 ;
1$
#264
0$
#265
1$
#266
0$
#267
1$
#268
0$
0(
#269
b110 =
1$
#270
0$
#271
1:
b100 =
1$
#272
0$
#273
0:
b0 =
b100000111000000 +
b100000111000000 6
b100000111000000 >
1$
#274
0$
#275
1$
#276
0$
#277
1$
#278
0$
b1001 *
#279
1$
#280
0$
#281
1$
#282
0$
#283
1$
#284
0$
#285
1$
#286
0$
#287
1$
#288
0$
1(
#289
b1 =
1$
#290
0$
#291
19
b11 =
1$
#292
0$
#293
09
b111 =
b1100000111000000 +
b1100000111000000 6
b1100000111000000 >
b1010 ;
1$
#294
0$
#295
1$
#296
0$
#297
1$
#298
0$
0(
#299
b110 =
1$
#300
0$
#301
1:
b100 =
1$
#302
0$
#303
0:
b0 =
b110000011100000 +
b110000011100000 6
b110000011100000 >
1$
#304
0$
#305
1$
#306
0$
#307
1$
#308
0$
b1010 *
#309
1$
#310
0$
#311
1$
#312
0$
#313
1$
#314
0$
#315
1$
#316
0$
#317
1$
#318
0$
1(
#319
b1 =
1$
#320
0$
#321
19
b11 =
1$
#322
0$
#323
09
b1110000011100000 +
b1110000011100000 6
b1110000011100000 >
b111 =
b1011 ;
1$
#324
0$
#325
1$
#326
0$
#327
1$
#328
0$
0(
#329
b110 =
1$
#330
0$
#331
1:
b100 =
1$
#332
0$
#333
0:
b0 =
b111000001110000 +
b111000001110000 6
b111000001110000 >
1$
#334
0$
#335
1$
#336
0$
#337
1$
#338
0$
b1011 *
#339
1$
#340
0$
#341
1$
#342
0$
#343
1$
#344
0$
#345
1$
#346
0$
#347
1$
#348
0$
1(
#349
b1 =
1$
#350
0$
#351
19
b11 =
1$
#352
0$
#353
09
b111 =
b1111000001110000 +
b1111000001110000 6
b1111000001110000 >
b1100 ;
1$
#354
0$
#355
1$
#356
0$
#357
1$
#358
0$
0(
#359
b110 =
1$
#360
0$
#361
1:
b100 =
1$
#362
0$
#363
0:
b0 =
b111100000111000 +
b111100000111000 6
b111100000111000 >
1$
#364
0$
#365
1$
#366
0$
#367
1$
#368
0$
0&
b1100 *
#369
1$
#370
0$
#371
1$
#372
0$
#373
1$
#374
0$
#375
1$
#376
0$
#377
1$
#378
0$
1(
#379
b1 =
1$
#380
0$
#381
19
b11 =
1$
#382
0$
#383
09
b111 =
b1101 ;
1$
#384
0$
#385
1$
#386
0$
#387
1$
#388
0$
0(
#389
b110 =
1$
#390
0$
#391
1:
b100 =
1$
#392
0$
#393
0:
b0 =
b11110000011100 +
b11110000011100 6
b11110000011100 >
1$
#394
0$
#395
1$
#396
0$
#397
1$
#398
0$
b1101 *
#399
1$
#400
0$
#401
1$
#402
0$
#403
1$
#404
0$
#405
1$
#406
0$
#407
1$
#408
0$
1(
#409
b1 =
1$
#410
0$
#411
19
b11 =
1$
#412
0$
#413
09
b111 =
b1110 ;
1$
#414
0$
#415
1$
#416
0$
#417
1$
#418
0$
0(
#419
b110 =
1$
#420
0$
#421
1:
b100 =
1$
#422
0$
#423
0:
b0 =
b1111000001110 +
b1111000001110 6
b1111000001110 >
1$
#424
0$
#425
1$
#426
0$
#427
1$
#428
0$
b1110 *
#429
1$
#430
0$
#431
1$
#432
0$
#433
1$
#434
0$
#435
1$
#436
0$
#437
1$
#438
0$
1(
#439
b1 =
1$
#440
0$
#441
19
b11 =
1$
#442
0$
#443
09
b111 =
b1111 ;
1$
#444
0$
#445
1$
#446
0$
#447
1$
#448
0$
0(
#449
b110 =
1$
#450
0$
#451
1:
b100 =
1$
#452
0$
#453
0:
b0 =
b111100000111 +
b111100000111 6
b111100000111 >
1$
#454
0$
#455
1$
#456
0$
#457
1$
#458
0$
b1111 *
#459
1$
#460
0$
#461
1$
#462
0$
#463
1$
#464
0$
#465
1$
#466
0$
#467
1$
#468
0$
1(
#469
b1 =
1$
#470
0$
#471
19
b11 =
1$
#472
0$
#473
09
b111 =
b10000 ;
1$
#474
0$
#475
1$
#476
0$
#477
1$
#478
0$
0(
#479
b110 =
1$
#480
0$
#481
1:
b100 =
1$
#482
0$
#483
0:
1,
1<
b0 =
1$
#484
0$
#485
0,
1.
b1111 0
b1111 3
b111 /
b111 2
1$
#486
0$
#487
11
0.
b0 0
b0 3
b0 /
b0 2
1$
#488
0$
1)
b10000 *
#489
1!
b1 ?
01
1$
#490
0$
#491
17
0!
b11 ?
1$
#492
0$
#493
07
b111 ?
1$
#494
0$
#495
1$
#496
0$
#497
1$
#498
0$
1&
b0 *
b10100011001 %
0)
#499
b110 ?
1$
#500
0$
#501
18
b100 ?
1$
#502
0$
#503
08
0<
b0 ;
b0 +
b0 6
b0 >
b0 ?
1$
#504
0$
#505
1$
#506
0$
#507
1$
#508
0$
1(
#509
b1 =
1$
#510
0$
#511
19
b11 =
1$
#512
0$
#513
09
b111 =
b1000000000000000 +
b1000000000000000 6
b1000000000000000 >
b1 ;
1$
#514
0$
#515
1$
#516
0$
#517
1$
#518
0$
0(
#519
b110 =
1$
#520
0$
#521
1:
b100 =
1$
#522
0$
#523
0:
b0 =
b100000000000000 +
b100000000000000 6
b100000000000000 >
1$
#524
0$
#525
1$
#526
0$
#527
1$
#528
0$
0&
b1 *
#529
1$
#530
0$
#531
1$
#532
0$
#533
1$
#534
0$
#535
1$
#536
0$
#537
1$
#538
0$
1(
#539
b1 =
1$
#540
0$
#541
19
b11 =
1$
#542
0$
#543
09
b111 =
b10 ;
1$
#544
0$
#545
1$
#546
0$
#547
1$
#548
0$
0(
#549
b110 =
1$
#550
0$
#551
1:
b100 =
1$
#552
0$
#553
0:
b0 =
b10000000000000 +
b10000000000000 6
b10000000000000 >
1$
#554
0$
#555
1$
#556
0$
#557
1$
#558
0$
b10 *
#559
1$
#560
0$
#561
1$
#562
0$
#563
1$
#564
0$
#565
1$
#566
0$
#567
1$
#568
0$
1(
#569
b1 =
1$
#570
0$
#571
19
b11 =
1$
#572
0$
#573
09
b111 =
b11 ;
1$
#574
0$
#575
1$
#576
0$
#577
1$
#578
0$
0(
#579
b110 =
1$
#580
0$
#581
1:
b100 =
1$
#582
0$
#583
0:
b0 =
b1000000000000 +
b1000000000000 6
b1000000000000 >
1$
#584
0$
#585
1$
#586
0$
#587
1$
#588
0$
1&
b11 *
#589
1$
#590
0$
#591
1$
#592
0$
#593
1$
#594
0$
#595
1$
#596
0$
#597
1$
#598
0$
1(
#599
b1 =
1$
#600
0$
#601
19
b11 =
1$
#602
0$
#603
09
b1001000000000000 +
b1001000000000000 6
b1001000000000000 >
b111 =
b100 ;
1$
#604
0$
#605
1$
#606
0$
#607
1$
#608
0$
0(
#609
b110 =
1$
#610
0$
#611
1:
b100 =
1$
#612
0$
#613
0:
b0 =
b100100000000000 +
b100100000000000 6
b100100000000000 >
1$
#614
0$
#615
1$
#616
0$
#617
1$
#618
0$
b100 *
#619
1$
#620
0$
#621
1$
#622
0$
#623
1$
#624
0$
#625
1$
#626
0$
#627
1$
#628
0$
1(
#629
b1 =
1$
#630
0$
#631
19
b11 =
1$
#632
0$
#633
09
b111 =
b1100100000000000 +
b1100100000000000 6
b1100100000000000 >
b101 ;
1$
#634
0$
#635
1$
#636
0$
#637
1$
#638
0$
0(
#639
b110 =
1$
#640
0$
#641
1:
b100 =
1$
#642
0$
#643
0:
b0 =
b110010000000000 +
b110010000000000 6
b110010000000000 >
1$
#644
0$
#645
1$
#646
0$
#647
1$
#648
0$
0&
b101 *
#649
1$
#650
0$
#651
1$
#652
0$
#653
1$
#654
0$
#655
1$
#656
0$
#657
1$
#658
0$
1(
#659
b1 =
1$
#660
0$
#661
19
b11 =
1$
#662
0$
#663
09
b111 =
b110 ;
1$
#664
0$
#665
1$
#666
0$
#667
1$
#668
0$
0(
#669
b110 =
1$
#670
0$
#671
1:
b100 =
1$
#672
0$
#673
0:
b0 =
b11001000000000 +
b11001000000000 6
b11001000000000 >
1$
#674
0$
#675
1$
#676
0$
#677
1$
#678
0$
b110 *
#679
1$
#680
0$
#681
1$
#682
0$
#683
1$
#684
0$
#685
1$
#686
0$
#687
1$
#688
0$
1(
#689
b1 =
1$
#690
0$
#691
19
b11 =
1$
#692
0$
#693
09
b111 =
b111 ;
1$
#694
0$
#695
1$
#696
0$
#697
1$
#698
0$
0(
#699
b110 =
1$
#700
0$
#701
1:
b100 =
1$
#702
0$
#703
0:
b0 =
b1100100000000 +
b1100100000000 6
b1100100000000 >
1$
#704
0$
#705
1$
#706
0$
#707
1$
#708
0$
b111 *
#709
1$
#710
0$
#711
1$
#712
0$
#713
1$
#714
0$
#715
1$
#716
0$
#717
1$
#718
0$
1(
#719
b1 =
1$
#720
0$
#721
19
b11 =
1$
#722
0$
#723
09
b111 =
b1000 ;
1$
#724
0$
#725
1$
#726
0$
#727
1$
#728
0$
0(
#729
b110 =
1$
#730
0$
#731
1:
b100 =
1$
#732
0$
#733
0:
b0 =
b110010000000 +
b110010000000 6
b110010000000 >
1$
#734
0$
#735
1$
#736
0$
#737
1$
#738
0$
1&
b1000 *
#739
1$
#740
0$
#741
1$
#742
0$
#743
1$
#744
0$
#745
1$
#746
0$
#747
1$
#748
0$
1(
#749
b1 =
1$
#750
0$
#751
19
b11 =
1$
#752
0$
#753
09
b111 =
b1000110010000000 +
b1000110010000000 6
b1000110010000000 >
b1001 ;
1$
#754
0$
#755
1$
#756
0$
#757
1$
#758
0$
0(
#759
b110 =
1$
#760
0$
#761
1:
b100 =
1$
#762
0$
#763
0:
b0 =
b100011001000000 +
b100011001000000 6
b100011001000000 >
1$
#764
0$
#765
1$
#766
0$
#767
1$
#768
0$
0&
b1001 *
#769
1$
#770
0$
#771
1$
#772
0$
#773
1$
#774
0$
#775
1$
#776
0$
#777
1$
#778
0$
1(
#779
b1 =
1$
#780
0$
#781
19
b11 =
1$
#782
0$
#783
09
b111 =
b1010 ;
1$
#784
0$
#785
1$
#786
0$
#787
1$
#788
0$
0(
#789
b110 =
1$
#790
0$
#791
1:
b100 =
1$
#792
0$
#793
0:
b0 =
b10001100100000 +
b10001100100000 6
b10001100100000 >
1$
#794
0$
#795
1$
#796
0$
#797
1$
#798
0$
1&
b1010 *
#799
1$
#800
0$
#801
1$
#802
0$
#803
1$
#804
0$
#805
1$
#806
0$
#807
1$
#808
0$
1(
#809
b1 =
1$
#810
0$
#811
19
b11 =
1$
#812
0$
#813
09
b111 =
b1010001100100000 +
b1010001100100000 6
b1010001100100000 >
b1011 ;
1$
#814
0$
#815
1$
#816
0$
#817
1$
#818
0$
0(
#819
b110 =
1$
#820
0$
#821
1:
b100 =
1$
#822
0$
#823
0:
b0 =
b101000110010000 +
b101000110010000 6
b101000110010000 >
1$
#824
0$
#825
1$
#826
0$
#827
1$
#828
0$
0&
b1011 *
#829
1$
#830
0$
#831
1$
#832
0$
#833
1$
#834
0$
#835
1$
#836
0$
#837
1$
#838
0$
1(
#839
b1 =
1$
#840
0$
#841
19
b11 =
1$
#842
0$
#843
09
b111 =
b1100 ;
1$
#844
0$
#845
1$
#846
0$
#847
1$
#848
0$
0(
#849
b110 =
1$
#850
0$
#851
1:
b100 =
1$
#852
0$
#853
0:
b0 =
b10100011001000 +
b10100011001000 6
b10100011001000 >
1$
#854
0$
#855
1$
#856
0$
#857
1$
#858
0$
b1100 *
#859
1$
#860
0$
#861
1$
#862
0$
#863
1$
#864
0$
#865
1$
#866
0$
#867
1$
#868
0$
1(
#869
b1 =
1$
#870
0$
#871
19
b11 =
1$
#872
0$
#873
09
b111 =
b1101 ;
1$
#874
0$
#875
1$
#876
0$
#877
1$
#878
0$
0(
#879
b110 =
1$
#880
0$
#881
1:
b100 =
1$
#882
0$
#883
0:
b0 =
b1010001100100 +
b1010001100100 6
b1010001100100 >
1$
#884
0$
#885
1$
#886
0$
#887
1$
#888
0$
b1101 *
#889
1$
#890
0$
#891
1$
#892
0$
#893
1$
#894
0$
#895
1$
#896
0$
#897
1$
#898
0$
1(
#899
b1 =
1$
#900
0$
#901
19
b11 =
1$
#902
0$
#903
09
b111 =
b1110 ;
1$
#904
0$
#905
1$
#906
0$
#907
1$
#908
0$
0(
#909
b110 =
1$
#910
0$
#911
1:
b100 =
1$
#912
0$
#913
0:
b0 =
b101000110010 +
b101000110010 6
b101000110010 >
1$
#914
0$
#915
1$
#916
0$
#917
1$
#918
0$
b1110 *
#919
1$
#920
0$
#921
1$
#922
0$
#923
1$
#924
0$
#925
1$
#926
0$
#927
1$
#928
0$
1(
#929
b1 =
1$
#930
0$
#931
19
b11 =
1$
#932
0$
#933
09
b111 =
b1111 ;
1$
#934
0$
#935
1$
#936
0$
#937
1$
#938
0$
0(
#939
b110 =
1$
#940
0$
#941
1:
b100 =
1$
#942
0$
#943
0:
b0 =
b10100011001 +
b10100011001 6
b10100011001 >
1$
#944
0$
#945
1$
#946
0$
#947
1$
#948
0$
b1111 *
#949
1$
#950
0$
#951
1$
#952
0$
#953
1$
#954
0$
#955
1$
#956
0$
#957
1$
#958
0$
1(
#959
b1 =
1$
#960
0$
#961
19
b11 =
1$
#962
0$
#963
09
b111 =
b10000 ;
1$
#964
0$
#965
1$
#966
0$
#967
1$
#968
0$
0(
#969
b110 =
1$
#970
0$
#971
1:
b100 =
1$
#972
0$
#973
0:
b0 =
1,
1<
1$
#974
0$
#975
1.
b101 0
b101 3
b11001 /
b11001 2
0,
1$
#976
0$
#977
11
0.
b0 0
b0 3
b0 /
b0 2
1$
#978
0$
1)
b10000 *
#979
1!
01
b1 ?
1$
#980
0$
#981
17
0!
b11 ?
1$
#982
0$
#983
07
b111 ?
1$
#984
0$
#985
1$
#986
0$
#987
1$
#988
0$
1&
b0 *
b10000100010001 %
0)
#989
b110 ?
1$
#990
0$
#991
18
b100 ?
1$
#992
0$
#993
08
b0 ?
0<
b0 ;
b0 +
b0 6
b0 >
1$
#994
0$
#995
1$
#996
0$
#997
1$
#998
0$
1(
#999
b1 =
1$
#1000
0$
#1001
19
b11 =
1$
#1002
0$
#1003
09
b1000000000000000 +
b1000000000000000 6
b1000000000000000 >
b111 =
b1 ;
1$
#1004
0$
#1005
1$
#1006
0$
#1007
1$
#1008
0$
0(
#1009
b110 =
1$
#1010
0$
#1011
1:
b100 =
1$
#1012
0$
#1013
0:
b0 =
b100000000000000 +
b100000000000000 6
b100000000000000 >
1$
#1014
0$
#1015
1$
#1016
0$
#1017
1$
#1018
0$
0&
b1 *
#1019
1$
#1020
0$
#1021
1$
#1022
0$
#1023
1$
#1024
0$
#1025
1$
#1026
0$
#1027
1$
#1028
0$
1(
#1029
b1 =
1$
#1030
0$
#1031
19
b11 =
1$
#1032
0$
#1033
09
b111 =
b10 ;
1$
#1034
0$
#1035
1$
#1036
0$
#1037
1$
#1038
0$
0(
#1039
b110 =
1$
#1040
0$
#1041
1:
b100 =
1$
#1042
0$
#1043
0:
b0 =
b10000000000000 +
b10000000000000 6
b10000000000000 >
1$
#1044
0$
#1045
1$
#1046
0$
#1047
1$
#1048
0$
b10 *
#1049
1$
#1050
0$
#1051
1$
#1052
0$
#1053
1$
#1054
0$
#1055
1$
#1056
0$
#1057
1$
#1058
0$
1(
#1059
b1 =
1$
#1060
0$
#1061
19
b11 =
1$
#1062
0$
#1063
09
b111 =
b11 ;
1$
#1064
0$
#1065
1$
#1066
0$
#1067
1$
#1068
0$
0(
#1069
b110 =
1$
#1070
0$
#1071
1:
b100 =
1$
#1072
0$
#1073
0:
b0 =
b1000000000000 +
b1000000000000 6
b1000000000000 >
1$
#1074
0$
#1075
1$
#1076
0$
#1077
1$
#1078
0$
b11 *
#1079
1$
#1080
0$
#1081
1$
#1082
0$
#1083
1$
#1084
0$
#1085
1$
#1086
0$
#1087
1$
#1088
0$
1(
#1089
b1 =
1$
#1090
0$
#1091
19
b11 =
1$
#1092
0$
#1093
09
b111 =
b100 ;
1$
#1094
0$
#1095
1$
#1096
0$
#1097
1$
#1098
0$
0(
#1099
b110 =
1$
#1100
0$
#1101
1:
b100 =
1$
#1102
0$
#1103
0:
b0 =
b100000000000 +
b100000000000 6
b100000000000 >
1$
#1104
0$
#1105
1$
#1106
0$
#1107
1$
#1108
0$
1&
b100 *
#1109
1$
#1110
0$
#1111
1$
#1112
0$
#1113
1$
#1114
0$
#1115
1$
#1116
0$
#1117
1$
#1118
0$
1(
#1119
b1 =
1$
#1120
0$
#1121
19
b11 =
1$
#1122
0$
#1123
09
b1000100000000000 +
b1000100000000000 6
b1000100000000000 >
b111 =
b101 ;
1$
#1124
0$
#1125
1$
#1126
0$
#1127
1$
#1128
0$
0(
#1129
b110 =
1$
#1130
0$
#1131
1:
b100 =
1$
#1132
0$
#1133
0:
b0 =
b100010000000000 +
b100010000000000 6
b100010000000000 >
1$
#1134
0$
#1135
1$
#1136
0$
#1137
1$
#1138
0$
0&
b101 *
#1139
1$
#1140
0$
#1141
1$
#1142
0$
#1143
1$
#1144
0$
#1145
1$
#1146
0$
#1147
1$
#1148
0$
1(
#1149
b1 =
1$
#1150
0$
#1151
19
b11 =
1$
#1152
0$
#1153
09
b111 =
b110 ;
1$
#1154
0$
#1155
1$
#1156
0$
#1157
1$
#1158
0$
0(
#1159
b110 =
1$
#1160
0$
#1161
1:
b100 =
1$
#1162
0$
#1163
0:
b0 =
b10001000000000 +
b10001000000000 6
b10001000000000 >
1$
#1164
0$
#1165
1$
#1166
0$
#1167
1$
#1168
0$
b110 *
#1169
1$
#1170
0$
#1171
1$
#1172
0$
#1173
1$
#1174
0$
#1175
1$
#1176
0$
#1177
1$
#1178
0$
1(
#1179
b1 =
1$
#1180
0$
#1181
19
b11 =
1$
#1182
0$
#1183
09
b111 =
b111 ;
1$
#1184
0$
#1185
1$
#1186
0$
#1187
1$
#1188
0$
0(
#1189
b110 =
1$
#1190
0$
