tarea4/rtl/multiplier.v
module mult(clk, din1, din2, start, rst, dout, ovf, ready);
  parameter N = 8;
  input clk;
  input [N-1:0] din1;
  input [N-1:0] din2;
  input start;
  input rst;
  output [N-1:0] dout;
  output ovf;
  output reg ready;

  reg [N-1:0] digit1;
  reg [N-1:0] digit2;
  reg [2*N-1:0] result;

  always @(posedge clk or rst) begin
    if (~rst) begin
      digit1 <= 0;
      digit2 <= 0;
      result <= 0;
    end
    else if (ready) begin
      ready <= 0;
    end
    else if (start) begin
      result <= din1 * din2;
      ready <= 1;
    end
  end

  // Outputs
  assign ovf = result[2*N-1:N] > 0;
  assign dout = ovf ? {N{1'b1}} : result[N-1:0];

  endmodule

tarea4/testbench/mult/mult_tb.v
`timescale 1ns/1ns
module mult_tb();
parameter N = 8;

initial begin
  $dumpfile("mult_tb.vcd");
  $dumpvars(0, mult_tb);
end

reg clk;
reg [N-1:0] din1;
reg [N-1:0] din2;
reg start;
reg rst;
wire [N-1:0] dout;
wire ovf;
wire ready;

mult #(.N(N))
  uut(.clk(clk),
      .din1(din1),
      .din2(din2),
      .start(start),
      .rst(rst),
      .dout(dout),
      .ovf(ovf),
      .ready(ready)
  );

initial begin
  clk = 0;
end

always #5 clk = ~clk;

initial begin

  rst = 0;
  din1 = 9;
  din2 = 3;
  start = 0;
  #10;

  rst = 1;
  #10;

  start = 1;
  #10;

  start = 0;
  #10;

  din1 = 50;
  din2 = 6;
  start = 1;
  #10;

  start = 0;
  #10

  $finish;

end






endmodule

tarea4/testbench/mult/mult_tb.vcd
$date
	Mon May 11 22:54:29 2020
$end
$version
	Icarus Verilog
$end
$timescale
	1ns
$end
$scope module mult_tb $end
$var wire 1 ! ready $end
$var wire 1 " ovf $end
$var wire 8 # dout [7:0] $end
$var reg 1 $ clk $end
$var reg 8 % din1 [7:0] $end
$var reg 8 & din2 [7:0] $end
$var reg 1 ' rst $end
$var reg 1 ( start $end
$scope module uut $end
$var wire 1 $ clk $end
$var wire 8 ) din1 [7:0] $end
$var wire 8 * din2 [7:0] $end
$var wire 1 ' rst $end
$var wire 1 ( start $end
$var wire 1 " ovf $end
$var wire 8 + dout [7:0] $end
$var reg 8 , digit1 [7:0] $end
$var reg 8 - digit2 [7:0] $end
$var reg 1 ! ready $end
$var reg 16 . result [15:0] $end
$upscope $end
$upscope $end
$enddefinitions $end
#0
$dumpvars
b0 .
b0 -
b0 ,
b0 +
b11 *
b1001 )
0(
0'
b11 &
b1001 %
0$
b0 #
0"
x!
$end
#5
1$
#10
0$
1'
#15
1$
#20
0$
1(
#25
b11011 #
b11011 +
1!
b11011 .
1$
#30
0$
0(
#35
0!
1$
#40
0$
1(
b110 &
b110 *
b110010 %
b110010 )
#45
b11111111 #
b11111111 +
1"
1!
b100101100 .
1$
#50
0$
0(
#55
0!
1$
